Metadata-Version: 1.0
Name: fbmsg
Version: 1.0.0
Summary: send facebook msg
Home-page: https://github.com/himanshu2454/facebook_msg_script
Author: Himanshu Chouahan
Author-email: hchouahan3654@gmail.com
License: UNKNOWN
Keywords: facebook,chat,messages
Platform: UNKNOWN
